pymakelib/__init__.py
pymakelib/addon.py
pymakelib/armsize.py
pymakelib/ceedling.py
pymakelib/eclipse_addon.py
pymakelib/eclipse_cproject.py
pymakelib/eclipse_files.py
pymakelib/exclude.py
pymakelib/generator.py
pymakelib/git.py
pymakelib/make_files.py
pymakelib/module.py
pymakelib/moduleignore.py
pymakelib/nproject.py
pymakelib/preconts.py
pymakelib/prelib.py
pymakelib/preutil.py
pymakelib/printsrc.py
pymakelib/project.py
pymakelib/pycodegen.py
pymakelib/pym.py
pymakelib/toolchain.py
pymakelib/vscode_addon.py
pymakelib/pynewproject_cproject/__init__.py
pymakelib/pynewproject_cproject/pynewproject_clinuxgcc.py
pymakelib/resources/__init__.py
pymakelib/resources/gtk/__init__.py
pymakelib/resources/gtk/pybagui.glade
pymakelib/resources/templates/__init__.py
pymakelib/resources/templates/clinuxgcc.tar.gz
pymaketool-2.0.6.data/scripts/pybuildanalyzer
pymaketool-2.0.6.data/scripts/pybuildanalyzer2
pymaketool-2.0.6.data/scripts/pymakedot
pymaketool-2.0.6.data/scripts/pymaketesting
pymaketool-2.0.6.data/scripts/pymaketool
pymaketool-2.0.6.data/scripts/pynewproject
pymaketool-2.0.6.dist-info/LICENSE
pymaketool-2.0.6.dist-info/METADATA
pymaketool-2.0.6.dist-info/WHEEL
pymaketool-2.0.6.dist-info/top_level.txt
pymaketool-2.0.6.dist-info/RECORD
