Metadata-Version: 2.1
Name: pymaketool
Version: 2.0.6
Summary: Python Makefile Tool
Home-page: https://github.com/ericsonj/pymaketool
Author: Ericson Joseph
Author-email: ericsonjoseph@gmail.com
License: MIT
Platform: UNKNOWN
Classifier: Programming Language :: Python :: 3
Classifier: License :: OSI Approved :: MIT License
Classifier: Operating System :: OS Independent
Requires-Python: >=3.6
License-File: LICENSE
Requires-Dist: prompt-toolkit
Requires-Dist: pathlib
